uv_test/__init__.py
uv_test-0.1.0.dist-info/METADATA
uv_test-0.1.0.dist-info/WHEEL
uv_test-0.1.0.dist-info/entry_points.txt
uv_test-0.1.0.dist-info/RECORD
